JiqiZhixin2019GaofenJiaochengJingyanFenxiangShenduHaowen/README.md
JiqiZhixin2019GaofenJiaochengJingyanFenxiangShenduHaowen/__init__.py
JiqiZhixin2019GaofenJiaochengJingyanFenxiangShenduHaowen/__main__.py
JiqiZhixin2019GaofenJiaochengJingyanFenxiangShenduHaowen/file.epub
JiqiZhixin2019GaofenJiaochengJingyanFenxiangShenduHaowen/index.html
JiqiZhixin2019GaofenJiaochengJingyanFenxiangShenduHaowen/css/__init__.py
JiqiZhixin2019GaofenJiaochengJingyanFenxiangShenduHaowen/css/annotations.css
JiqiZhixin2019GaofenJiaochengJingyanFenxiangShenduHaowen/css/main.css
JiqiZhixin2019GaofenJiaochengJingyanFenxiangShenduHaowen/css/normalize.css
JiqiZhixin2019GaofenJiaochengJingyanFenxiangShenduHaowen/css/popup.css
JiqiZhixin2019GaofenJiaochengJingyanFenxiangShenduHaowen/font/__init__.py
JiqiZhixin2019GaofenJiaochengJingyanFenxiangShenduHaowen/font/fontello.eot
JiqiZhixin2019GaofenJiaochengJingyanFenxiangShenduHaowen/font/fontello.svg
JiqiZhixin2019GaofenJiaochengJingyanFenxiangShenduHaowen/font/fontello.ttf
JiqiZhixin2019GaofenJiaochengJingyanFenxiangShenduHaowen/font/fontello.woff
JiqiZhixin2019GaofenJiaochengJingyanFenxiangShenduHaowen/img/__init__.py
JiqiZhixin2019GaofenJiaochengJingyanFenxiangShenduHaowen/img/annotator-glyph-sprite.png
JiqiZhixin2019GaofenJiaochengJingyanFenxiangShenduHaowen/img/annotator-icon-sprite.png
JiqiZhixin2019GaofenJiaochengJingyanFenxiangShenduHaowen/img/apple-touch-icon.png
JiqiZhixin2019GaofenJiaochengJingyanFenxiangShenduHaowen/img/cancelfullscreen.png
JiqiZhixin2019GaofenJiaochengJingyanFenxiangShenduHaowen/img/close.png
JiqiZhixin2019GaofenJiaochengJingyanFenxiangShenduHaowen/img/fullscreen.png
JiqiZhixin2019GaofenJiaochengJingyanFenxiangShenduHaowen/img/loader.gif
JiqiZhixin2019GaofenJiaochengJingyanFenxiangShenduHaowen/img/menu-icon.png
JiqiZhixin2019GaofenJiaochengJingyanFenxiangShenduHaowen/img/save.png
JiqiZhixin2019GaofenJiaochengJingyanFenxiangShenduHaowen/img/saved.png
jiqi_zhixin_2019_gaofen_jiaocheng_jingyan_fenxiang_shendu_haowen-2024.3.5.0.dist-info/METADATA
jiqi_zhixin_2019_gaofen_jiaocheng_jingyan_fenxiang_shendu_haowen-2024.3.5.0.dist-info/WHEEL
jiqi_zhixin_2019_gaofen_jiaocheng_jingyan_fenxiang_shendu_haowen-2024.3.5.0.dist-info/entry_points.txt
jiqi_zhixin_2019_gaofen_jiaocheng_jingyan_fenxiang_shendu_haowen-2024.3.5.0.dist-info/top_level.txt
jiqi_zhixin_2019_gaofen_jiaocheng_jingyan_fenxiang_shendu_haowen-2024.3.5.0.dist-info/RECORD
